[
  {
    "pid": 149440201013,
    "tid": 8807455743,
    "user_name": "",
    "user_id": 6572578148,
    "text": "。",
    "time": 1703477162,
    "image_links": [],
    "img_urls_original": [],
    "is_comment": false,
    "parent_pid": null,
    "floor": 606
  },
  {
    "pid": 149440201799,
    "tid": 8807455743,
    "user_name": "忆昨夜挑灯看剑",
    "user_id": 6529682103,
    "text": "3\n我曾三度遭到背叛",
    "time": 1703477167,
    "image_links": [],
    "img_urls_original": [],
    "is_comment": false,
    "parent_pid": null,
    "floor": 607
  },
  {
    "pid": 149440340776,
    "tid": 8807455743,
    "user_name": "血雨公爵",
    "user_id": 893898138,
    "text": "6666",
    "time": 1703477997,
    "image_links": [],
    "img_urls_original": [],
    "is_comment": false,
    "parent_pid": null,
    "floor": 608
  },
  {
    "pid": 149440358246,
    "tid": 8807455743,
    "user_name": "天明IIii",
    "user_id": 2472066263,
    "text": "(☆_☆)\n13007",
    "time": 1703478098,
    "image_links": [],
    "img_urls_original": [],
    "is_comment": false,
    "parent_pid": null,
    "floor": 609
  },
  {
    "pid": 149440483785,
    "tid": 8807455743,
    "user_name": "2222了40",
    "user_id": 4073645997,
    "text": "1",
    "time": 1703478834,
    "image_links": [],
    "img_urls_original": [],
    "is_comment": false,
    "parent_pid": null,
    "floor": 610
  },
  {
    "pid": 149440546237,
    "tid": 8807455743,
    "user_name": "FJIHRBKDO",
    "user_id": 3355649025,
    "text": "还不更新，夜不能寐",
    "time": 1703479194,
    "image_links": [],
    "img_urls_original": [],
    "is_comment": false,
    "parent_pid": null,
    "floor": 611
  },
  {
    "pid": 149440674130,
    "tid": 8807455743,
    "user_name": "花开花落的节",
    "user_id": 1672513033,
    "text": "3",
    "time": 1703479936,
    "image_links": [],
    "img_urls_original": [],
    "is_comment": false,
    "parent_pid": null,
    "floor": 613
  },
  {
    "pid": 149440726895,
    "tid": 8807455743,
    "user_name": "mijun115532",
    "user_id": 859805479,
    "text": "3",
    "time": 1703480236,
    "image_links": [],
    "img_urls_original": [],
    "is_comment": false,
    "parent_pid": null,
    "floor": 615
  },
  {
    "pid": 149440727556,
    "tid": 8807455743,
    "user_name": "mijun115532",
    "user_id": 859805479,
    "text": "3",
    "time": 1703480240,
    "image_links": [],
    "img_urls_original": [],
    "is_comment": false,
    "parent_pid": null,
    "floor": 616
  },
  {
    "pid": 149440728184,
    "tid": 8807455743,
    "user_name": "mijun115532",
    "user_id": 859805479,
    "text": "3",
    "time": 1703480243,
    "image_links": [],
    "img_urls_original": [],
    "is_comment": false,
    "parent_pid": null,
    "floor": 617
  },
  {
    "pid": 149440728720,
    "tid": 8807455743,
    "user_name": "mijun115532",
    "user_id": 859805479,
    "text": "3",
    "time": 1703480246,
    "image_links": [],
    "img_urls_original": [],
    "is_comment": false,
    "parent_pid": null,
    "floor": 618
  },
  {
    "pid": 149440729211,
    "tid": 8807455743,
    "user_name": "mijun115532",
    "user_id": 859805479,
    "text": "3",
    "time": 1703480249,
    "image_links": [],
    "img_urls_original": [],
    "is_comment": false,
    "parent_pid": null,
    "floor": 619
  },
  {
    "pid": 149440813484,
    "tid": 8807455743,
    "user_name": "非洲酋长比利君",
    "user_id": 1644187456,
    "text": "快快快",
    "time": 1703480746,
    "image_links": [],
    "img_urls_original": [],
    "is_comment": false,
    "parent_pid": null,
    "floor": 621
  },
  {
    "pid": 149440857827,
    "tid": 8807455743,
    "user_name": "游戏搬砖的",
    "user_id": 4579299327,
    "text": "1",
    "time": 1703481014,
    "image_links": [],
    "img_urls_original": [],
    "is_comment": false,
    "parent_pid": null,
    "floor": 622
  },
  {
    "pid": 149440866491,
    "tid": 8807455743,
    "user_name": "痪蔼蒜蔼",
    "user_id": 2049509242,
    "text": "哈哈，已下载",
    "time": 1703481066,
    "image_links": [],
    "img_urls_original": [],
    "is_comment": false,
    "parent_pid": null,
    "floor": 623
  },
  {
    "pid": 149440883422,
    "tid": 8807455743,
    "user_name": "一个机会的命",
    "user_id": 4351075101,
    "text": "生产队的驴都不敢这么歇",
    "time": 1703481164,
    "image_links": [],
    "img_urls_original": [],
    "is_comment": false,
    "parent_pid": null,
    "floor": 624
  },
  {
    "pid": 149440893518,
    "tid": 8807455743,
    "user_name": "东山吴秀丽",
    "user_id": 2900589405,
    "text": "🛋️",
    "time": 1703481222,
    "image_links": [],
    "img_urls_original": [],
    "is_comment": false,
    "parent_pid": null,
    "floor": 625
  },
  {
    "pid": 149440920305,
    "tid": 8807455743,
    "user_name": "麦克腾瑟",
    "user_id": 6545293091,
    "text": "一",
    "time": 1703481372,
    "image_links": [],
    "img_urls_original": [],
    "is_comment": false,
    "parent_pid": null,
    "floor": 626
  },
  {
    "pid": 149440932151,
    "tid": 8807455743,
    "user_name": "",
    "user_id": 6571958233,
    "text": "哈哈哈哈",
    "time": 1703481440,
    "image_links": [],
    "img_urls_original": [],
    "is_comment": false,
    "parent_pid": null,
    "floor": 627
  },
  {
    "pid": 149440946000,
    "tid": 8807455743,
    "user_name": "酷萌plus",
    "user_id": 2730589257,
    "text": "请假后在去公司上班算不算加班啊",
    "time": 1703481522,
    "image_links": [],
    "img_urls_original": [],
    "is_comment": false,
    "parent_pid": null,
    "floor": 628
  },
  {
    "pid": 149440996960,
    "tid": 8807455743,
    "user_name": "风已去兮花满楼",
    "user_id": 1073238422,
    "text": "3",
    "time": 1703481820,
    "image_links": [],
    "img_urls_original": [],
    "is_comment": false,
    "parent_pid": null,
    "floor": 630
  },
  {
    "pid": 149441076339,
    "tid": 8807455743,
    "user_name": "一样与不同",
    "user_id": 2090788142,
    "text": "我不知道",
    "time": 1703482276,
    "image_links": [],
    "img_urls_original": [],
    "is_comment": false,
    "parent_pid": null,
    "floor": 634
  },
  {
    "pid": 149441187589,
    "tid": 8807455743,
    "user_name": "浅然久爱不腻",
    "user_id": 821400038,
    "text": "1",
    "time": 1703482931,
    "image_links": [],
    "img_urls_original": [],
    "is_comment": false,
    "parent_pid": null,
    "floor": 635
  },
  {
    "pid": 149441291598,
    "tid": 8807455743,
    "user_name": "柴犬Misaki",
    "user_id": 1553729796,
    "text": "哈哈",
    "time": 1703483543,
    "image_links": [],
    "img_urls_original": [],
    "is_comment": false,
    "parent_pid": null,
    "floor": 638
  },
  {
    "pid": 149441318211,
    "tid": 8807455743,
    "user_name": "",
    "user_id": 1019520767,
    "text": "cy",
    "time": 1703483693,
    "image_links": [],
    "img_urls_original": [],
    "is_comment": false,
    "parent_pid": null,
    "floor": 639
  },
  {
    "pid": 149441364603,
    "tid": 8807455743,
    "user_name": "",
    "user_id": 3515946365,
    "text": "滴滴",
    "time": 1703483958,
    "image_links": [],
    "img_urls_original": [],
    "is_comment": false,
    "parent_pid": null,
    "floor": 641
  },
  {
    "pid": 149441451438,
    "tid": 8807455743,
    "user_name": "木子李15260",
    "user_id": 1640691636,
    "text": "666",
    "time": 1703484471,
    "image_links": [],
    "img_urls_original": [],
    "is_comment": false,
    "parent_pid": null,
    "floor": 647
  },
  {
    "pid": 149441451672,
    "tid": 8807455743,
    "user_name": "Messiisinfin",
    "user_id": 3545579429,
    "text": "1",
    "time": 1703484472,
    "image_links": [],
    "img_urls_original": [],
    "is_comment": false,
    "parent_pid": null,
    "floor": 648
  }
]