[
  {
    "pid": 139387952257,
    "tid": 7339397421,
    "user_name": "公孙闬",
    "user_id": 384316858,
    "text": "85.哆啦A梦从事微商后改名“A哆啦梦”。",
    "time": 1621418366,
    "image_links": [],
    "img_urls_original": [],
    "is_comment": false,
    "parent_pid": null,
    "floor": 915
  },
  {
    "pid": 139387953923,
    "tid": 7339397421,
    "user_name": "公孙闬",
    "user_id": 384316858,
    "text": "84.半径越大，直径越大",
    "time": 1621418373,
    "image_links": [],
    "img_urls_original": [],
    "is_comment": false,
    "parent_pid": null,
    "floor": 916
  },
  {
    "pid": 139387955374,
    "tid": 7339397421,
    "user_name": "公孙闬",
    "user_id": 384316858,
    "text": "83.种族歧视又叫做以色列人",
    "time": 1621418379,
    "image_links": [],
    "img_urls_original": [],
    "is_comment": false,
    "parent_pid": null,
    "floor": 917
  },
  {
    "pid": 139387956620,
    "tid": 7339397421,
    "user_name": "公孙闬",
    "user_id": 384316858,
    "text": "82.我不同意你的观点，但我誓死捍卫我不同意你观点的权利。",
    "time": 1621418384,
    "image_links": [],
    "img_urls_original": [],
    "is_comment": false,
    "parent_pid": null,
    "floor": 918
  },
  {
    "pid": 139387958150,
    "tid": 7339397421,
    "user_name": "公孙闬",
    "user_id": 384316858,
    "text": "81.我觉得我就是酚，除了苯，就是醇。",
    "time": 1621418390,
    "image_links": [],
    "img_urls_original": [],
    "is_comment": false,
    "parent_pid": null,
    "floor": 919
  },
  {
    "pid": 139387961268,
    "tid": 7339397421,
    "user_name": "公孙闬",
    "user_id": 384316858,
    "text": "80.田忌赛马，吉普赛人。\n木已成舟，蚂蚁森林。\n臣本布衣，草本植物。\n十年树木，一周树人。",
    "time": 1621418402,
    "image_links": [],
    "img_urls_original": [],
    "is_comment": false,
    "parent_pid": null,
    "floor": 920
  },
  {
    "pid": 139391022458,
    "tid": 7339397421,
    "user_name": "公孙闬",
    "user_id": 384316858,
    "text": "79.为什么说老师是园丁，因为园丁的工作就是把植物摆弄成自己想要的造型。",
    "time": 1621429182,
    "image_links": [],
    "img_urls_original": [],
    "is_comment": false,
    "parent_pid": null,
    "floor": 921
  },
  {
    "pid": 139391024223,
    "tid": 7339397421,
    "user_name": "公孙闬",
    "user_id": 384316858,
    "text": "78.一日为师终身为父，小明跪在病逝的小学老师灵前，和老师的几个子女争起了遗产",
    "time": 1621429188,
    "image_links": [],
    "img_urls_original": [],
    "is_comment": false,
    "parent_pid": null,
    "floor": 922
  },
  {
    "pid": 139391026013,
    "tid": 7339397421,
    "user_name": "公孙闬",
    "user_id": 384316858,
    "text": "77.昨天出门的时候脚不小心踩到地球了，一直黏在我脚上怎么甩也甩不掉，好恶心",
    "time": 1621429194,
    "image_links": [],
    "img_urls_original": [],
    "is_comment": false,
    "parent_pid": null,
    "floor": 923
  },
  {
    "pid": 139391028790,
    "tid": 7339397421,
    "user_name": "公孙闬",
    "user_id": 384316858,
    "text": "75.我们的身体里藏着一具骷髅。",
    "time": 1621429204,
    "image_links": [],
    "img_urls_original": [],
    "is_comment": false,
    "parent_pid": null,
    "floor": 925
  },
  {
    "pid": 139391030566,
    "tid": 7339397421,
    "user_name": "公孙闬",
    "user_id": 384316858,
    "text": "74.红萝卜说白了就是白萝卜",
    "time": 1621429209,
    "image_links": [],
    "img_urls_original": [],
    "is_comment": false,
    "parent_pid": null,
    "floor": 926
  },
  {
    "pid": 139391032505,
    "tid": 7339397421,
    "user_name": "公孙闬",
    "user_id": 384316858,
    "text": "73.语文老师告诉我作文结尾最好要有升华，于是我在结尾写下了樟脑丸在柜子里变小的例子。",
    "time": 1621429216,
    "image_links": [],
    "img_urls_original": [],
    "is_comment": false,
    "parent_pid": null,
    "floor": 927
  },
  {
    "pid": 139391034796,
    "tid": 7339397421,
    "user_name": "公孙闬",
    "user_id": 384316858,
    "text": "72.视力检查加入高考，学校家长纷纷让学生背诵视力表",
    "time": 1621429224,
    "image_links": [],
    "img_urls_original": [],
    "is_comment": false,
    "parent_pid": null,
    "floor": 928
  },
  {
    "pid": 139391037289,
    "tid": 7339397421,
    "user_name": "公孙闬",
    "user_id": 384316858,
    "text": "71.“我找到一样东西。”\n“什么东西？”\n“和你聊天的借口。”",
    "time": 1621429232,
    "image_links": [],
    "img_urls_original": [],
    "is_comment": false,
    "parent_pid": null,
    "floor": 929
  },
  {
    "pid": 139391039287,
    "tid": 7339397421,
    "user_name": "公孙闬",
    "user_id": 384316858,
    "text": "70.老师问同学文章的点睛之笔在哪行，同学们直呼内行",
    "time": 1621429239,
    "image_links": [],
    "img_urls_original": [],
    "is_comment": false,
    "parent_pid": null,
    "floor": 930
  },
  {
    "pid": 139391356449,
    "tid": 7339397421,
    "user_name": "公孙闬",
    "user_id": 384316858,
    "text": "69.熬夜的人是不是单纯的想拒绝第二天的到来呢?",
    "time": 1621430226,
    "image_links": [],
    "img_urls_original": [],
    "is_comment": false,
    "parent_pid": null,
    "floor": 931
  },
  {
    "pid": 139391361018,
    "tid": 7339397421,
    "user_name": "公孙闬",
    "user_id": 384316858,
    "text": "68.“我是高中生”\n“我是高中生”\n“你不是高考完了吗？”\n“我复读了”",
    "time": 1621430240,
    "image_links": [],
    "img_urls_original": [],
    "is_comment": false,
    "parent_pid": null,
    "floor": 932
  },
  {
    "pid": 139391362771,
    "tid": 7339397421,
    "user_name": "公孙闬",
    "user_id": 384316858,
    "text": "67.研究人员表明《流浪地球》有语病，应改为“流浪的球”。",
    "time": 1621430245,
    "image_links": [],
    "img_urls_original": [],
    "is_comment": false,
    "parent_pid": null,
    "floor": 933
  },
  {
    "pid": 139391364540,
    "tid": 7339397421,
    "user_name": "公孙闬",
    "user_id": 384316858,
    "text": "66.为了应对网友们“网抑云音乐”的嘲讽，网易云音乐决定把音乐的乐改成快乐的乐。",
    "time": 1621430250,
    "image_links": [],
    "img_urls_original": [],
    "is_comment": false,
    "parent_pid": null,
    "floor": 934
  },
  {
    "pid": 139391366694,
    "tid": 7339397421,
    "user_name": "公孙闬",
    "user_id": 384316858,
    "text": "65.你青春期三分之二的烦恼都来自父母，他们却试图帮你疏解烦恼。",
    "time": 1621430257,
    "image_links": [],
    "img_urls_original": [],
    "is_comment": false,
    "parent_pid": null,
    "floor": 935
  },
  {
    "pid": 139391369028,
    "tid": 7339397421,
    "user_name": "公孙闬",
    "user_id": 384316858,
    "text": "64.找到我们广告跳过按钮的用户将奖励安装包一个",
    "time": 1621430264,
    "image_links": [],
    "img_urls_original": [],
    "is_comment": false,
    "parent_pid": null,
    "floor": 936
  },
  {
    "pid": 139391374043,
    "tid": 7339397421,
    "user_name": "公孙闬",
    "user_id": 384316858,
    "text": "63.敬老院的新人都是老人，世界上的大人都是小人",
    "time": 1621430279,
    "image_links": [],
    "img_urls_original": [],
    "is_comment": false,
    "parent_pid": null,
    "floor": 937
  },
  {
    "pid": 139391375684,
    "tid": 7339397421,
    "user_name": "公孙闬",
    "user_id": 384316858,
    "text": "62.我把我的手表调快了一分钟，就这样遇到了本该错过的你。",
    "time": 1621430285,
    "image_links": [],
    "img_urls_original": [],
    "is_comment": false,
    "parent_pid": null,
    "floor": 938
  },
  {
    "pid": 139391377389,
    "tid": 7339397421,
    "user_name": "公孙闬",
    "user_id": 384316858,
    "text": "61.观刈麦也叫杀死那个拾稼庄人。",
    "time": 1621430290,
    "image_links": [],
    "img_urls_original": [],
    "is_comment": false,
    "parent_pid": null,
    "floor": 939
  },
  {
    "pid": 139391379004,
    "tid": 7339397421,
    "user_name": "公孙闬",
    "user_id": 384316858,
    "text": "60.爱是两个人眼睛间不断来回反射的光",
    "time": 1621430295,
    "image_links": [],
    "img_urls_original": [],
    "is_comment": false,
    "parent_pid": null,
    "floor": 940
  },
  {
    "pid": 139393651801,
    "tid": 7339397421,
    "user_name": "用户您太长",
    "user_id": 4077197513,
    "text": "冲！",
    "time": 1621437426,
    "image_links": [],
    "img_urls_original": [],
    "is_comment": false,
    "parent_pid": null,
    "floor": 941
  },
  {
    "pid": 139394158477,
    "tid": 7339397421,
    "user_name": "公孙闬",
    "user_id": 384316858,
    "text": "59.“老鼠呢！？”“这狗老鼠猫起来了”",
    "time": 1621439110,
    "image_links": [],
    "img_urls_original": [],
    "is_comment": false,
    "parent_pid": null,
    "floor": 942
  },
  {
    "pid": 139394200824,
    "tid": 7339397421,
    "user_name": "公孙闬",
    "user_id": 384316858,
    "text": "58.“这丨t丨m丨是什么破歌啊！”\n“茅屋为秋风所破歌”",
    "time": 1621439258,
    "image_links": [],
    "img_urls_original": [],
    "is_comment": false,
    "parent_pid": null,
    "floor": 951
  },
  {
    "pid": 139394204324,
    "tid": 7339397421,
    "user_name": "公孙闬",
    "user_id": 384316858,
    "text": "57.躺在床上第十八天的我突然泛起一阵恶心，原来是活腻了。",
    "time": 1621439271,
    "image_links": [],
    "img_urls_original": [],
    "is_comment": false,
    "parent_pid": null,
    "floor": 952
  },
  {
    "pid": 139394205981,
    "tid": 7339397421,
    "user_name": "公孙闬",
    "user_id": 384316858,
    "text": "56.年轻人注意了！身上出现这4种尸斑，是你的身体在对你发出警报！",
    "time": 1621439276,
    "image_links": [],
    "img_urls_original": [],
    "is_comment": false,
    "parent_pid": null,
    "floor": 953
  }
]