[
  {
    "pid": 139270674634,
    "tid": 7339397421,
    "user_name": "公孙闬",
    "user_id": 384316858,
    "text": "175.半夜鬼敲门，说明鬼有礼貌。",
    "time": 1620842698,
    "image_links": [],
    "img_urls_original": [],
    "is_comment": false,
    "parent_pid": null,
    "floor": 786
  },
  {
    "pid": 139270675114,
    "tid": 7339397421,
    "user_name": "公孙闬",
    "user_id": 384316858,
    "text": "174.后宫不得干政，始皇帝只能手冲。",
    "time": 1620842703,
    "image_links": [],
    "img_urls_original": [],
    "is_comment": false,
    "parent_pid": null,
    "floor": 787
  },
  {
    "pid": 139270675633,
    "tid": 7339397421,
    "user_name": "公孙闬",
    "user_id": 384316858,
    "text": "173.在网上看到很多人推荐批判从众心理的《乌合之众》，我也跟着他们去看了。",
    "time": 1620842708,
    "image_links": [],
    "img_urls_original": [],
    "is_comment": false,
    "parent_pid": null,
    "floor": 788
  },
  {
    "pid": 139270676070,
    "tid": 7339397421,
    "user_name": "公孙闬",
    "user_id": 384316858,
    "text": "172.“我们的人从不守法。”1940年的巴黎士兵说道。",
    "time": 1620842712,
    "image_links": [],
    "img_urls_original": [],
    "is_comment": false,
    "parent_pid": null,
    "floor": 789
  },
  {
    "pid": 139270676881,
    "tid": 7339397421,
    "user_name": "公孙闬",
    "user_id": 384316858,
    "text": "171.如果你想找意中人，可以去梵蒂冈找找看。",
    "time": 1620842721,
    "image_links": [],
    "img_urls_original": [],
    "is_comment": false,
    "parent_pid": null,
    "floor": 790
  },
  {
    "pid": 139270901518,
    "tid": 7339397421,
    "user_name": "伟大的九xi",
    "user_id": 1679273599,
    "text": "直播！！！好耶",
    "time": 1620845217,
    "image_links": [],
    "img_urls_original": [],
    "is_comment": false,
    "parent_pid": null,
    "floor": 791
  },
  {
    "pid": 139272938576,
    "tid": 7339397421,
    "user_name": "浅唱0呐爱",
    "user_id": 718356079,
    "text": "gkd",
    "time": 1620867039,
    "image_links": [],
    "img_urls_original": [],
    "is_comment": false,
    "parent_pid": null,
    "floor": 792
  },
  {
    "pid": 139274048577,
    "tid": 7339397421,
    "user_name": "",
    "user_id": 4308288332,
    "text": "",
    "time": 1620871757,
    "image_links": [
      "images/楼层_793_139274048577_图片1.jpg"
    ],
    "img_urls_original": [
      "http://tiebapic.baidu.com/forum/pic/item/b03ff9faaf51f3de8ebd9cd583eef01f3a297918.jpg?tbpicau=2026-03-19-05_475c6805ce484ab8de6117e07237ad10"
    ],
    "is_comment": false,
    "parent_pid": null,
    "floor": 793
  },
  {
    "pid": 139275167463,
    "tid": 7339397421,
    "user_name": "跌卡鲁恰巴萨拉",
    "user_id": 3925920129,
    "text": "怎么投稿微博呢",
    "time": 1620875994,
    "image_links": [],
    "img_urls_original": [],
    "is_comment": false,
    "parent_pid": null,
    "floor": 794
  },
  {
    "pid": 139280264219,
    "tid": 7339397421,
    "user_name": "小丫么小黑",
    "user_id": 3027513585,
    "text": "插眼",
    "time": 1620895935,
    "image_links": [],
    "img_urls_original": [],
    "is_comment": false,
    "parent_pid": null,
    "floor": 795
  },
  {
    "pid": 139280711102,
    "tid": 7339397421,
    "user_name": "Zk凯ai",
    "user_id": 1230694416,
    "text": "笑嘻了@🌌星辰海洋",
    "time": 1620897580,
    "image_links": [],
    "img_urls_original": [],
    "is_comment": false,
    "parent_pid": null,
    "floor": 796
  },
  {
    "pid": 139280932074,
    "tid": 7339397421,
    "user_name": "alooooohaysh08",
    "user_id": 1055157263,
    "text": "插插插插插插插插插！",
    "time": 1620898412,
    "image_links": [],
    "img_urls_original": [],
    "is_comment": false,
    "parent_pid": null,
    "floor": 797
  },
  {
    "pid": 139282640710,
    "tid": 7339397421,
    "user_name": "暗影屁屁",
    "user_id": 2653263545,
    "text": "插！",
    "time": 1620904981,
    "image_links": [],
    "img_urls_original": [],
    "is_comment": false,
    "parent_pid": null,
    "floor": 798
  },
  {
    "pid": 139284559790,
    "tid": 7339397421,
    "user_name": "喜欢笑么_",
    "user_id": 2727104486,
    "text": "插👀",
    "time": 1620911779,
    "image_links": [],
    "img_urls_original": [],
    "is_comment": false,
    "parent_pid": null,
    "floor": 799
  },
  {
    "pid": 139291293592,
    "tid": 7339397421,
    "user_name": "书虫之殇",
    "user_id": 1109440700,
    "text": "cy",
    "time": 1620956473,
    "image_links": [],
    "img_urls_original": [],
    "is_comment": false,
    "parent_pid": null,
    "floor": 800
  },
  {
    "pid": 139292431408,
    "tid": 7339397421,
    "user_name": "卫宫saber切嗣",
    "user_id": 1684174938,
    "text": "gkd",
    "time": 1620960667,
    "image_links": [],
    "img_urls_original": [],
    "is_comment": false,
    "parent_pid": null,
    "floor": 801
  },
  {
    "pid": 139298366325,
    "tid": 7339397421,
    "user_name": "miku咪扣",
    "user_id": 3574807786,
    "text": "gkd",
    "time": 1620985008,
    "image_links": [],
    "img_urls_original": [],
    "is_comment": false,
    "parent_pid": null,
    "floor": 803
  },
  {
    "pid": 139298427468,
    "tid": 7339397421,
    "user_name": "超能失控人",
    "user_id": 2771727016,
    "text": "gkd",
    "time": 1620985283,
    "image_links": [],
    "img_urls_original": [],
    "is_comment": false,
    "parent_pid": null,
    "floor": 804
  },
  {
    "pid": 139298881274,
    "tid": 7339397421,
    "user_name": "公孙闬",
    "user_id": 384316858,
    "text": "170.写论文太入迷晕倒了，清醒过来后“水...水...水”导师把我写的论文塞我嘴里了",
    "time": 1620987257,
    "image_links": [],
    "img_urls_original": [],
    "is_comment": false,
    "parent_pid": null,
    "floor": 806
  },
  {
    "pid": 139298885962,
    "tid": 7339397421,
    "user_name": "公孙闬",
    "user_id": 384316858,
    "text": "169.他骨子里充满了骨髓",
    "time": 1620987277,
    "image_links": [],
    "img_urls_original": [],
    "is_comment": false,
    "parent_pid": null,
    "floor": 807
  },
  {
    "pid": 139298887423,
    "tid": 7339397421,
    "user_name": "公孙闬",
    "user_id": 384316858,
    "text": "168.子在川上曰：逝者如斯夫不舍昼夜。子在川中曰：救命",
    "time": 1620987284,
    "image_links": [],
    "img_urls_original": [],
    "is_comment": false,
    "parent_pid": null,
    "floor": 808
  },
  {
    "pid": 139298889033,
    "tid": 7339397421,
    "user_name": "公孙闬",
    "user_id": 384316858,
    "text": "167.一个水蛭问另一个水蛭说：你为什么抓不到食物？另一个水蛭回答说：“因为我是弱蛭”",
    "time": 1620987290,
    "image_links": [],
    "img_urls_original": [],
    "is_comment": false,
    "parent_pid": null,
    "floor": 809
  },
  {
    "pid": 139298890304,
    "tid": 7339397421,
    "user_name": "公孙闬",
    "user_id": 384316858,
    "text": "166.这栋楼因格格不入建筑风格吸引了大量蓝精灵入住。",
    "time": 1620987296,
    "image_links": [],
    "img_urls_original": [],
    "is_comment": false,
    "parent_pid": null,
    "floor": 810
  },
  {
    "pid": 139298895744,
    "tid": 7339397421,
    "user_name": "公孙闬",
    "user_id": 384316858,
    "text": "165.“爸爸！你会唱小星星吗？”“**你个**！***写**完作业了吗？****！”",
    "time": 1620987319,
    "image_links": [],
    "img_urls_original": [],
    "is_comment": false,
    "parent_pid": null,
    "floor": 811
  },
  {
    "pid": 139298897014,
    "tid": 7339397421,
    "user_name": "公孙闬",
    "user_id": 384316858,
    "text": "164.如何称呼一个3.14m³的小星球？π大星。",
    "time": 1620987324,
    "image_links": [],
    "img_urls_original": [],
    "is_comment": false,
    "parent_pid": null,
    "floor": 812
  },
  {
    "pid": 139298898440,
    "tid": 7339397421,
    "user_name": "公孙闬",
    "user_id": 384316858,
    "text": "163.“王先生，恭喜你啊!是个男孩。”王老汉雇的私人侦探调查他儿子的恋人后向他报告。",
    "time": 1620987330,
    "image_links": [],
    "img_urls_original": [],
    "is_comment": false,
    "parent_pid": null,
    "floor": 813
  },
  {
    "pid": 139298900070,
    "tid": 7339397421,
    "user_name": "公孙闬",
    "user_id": 384316858,
    "text": "162.看见最近的机票很便宜，我赶紧把房子卖了全部买进等着疫情过后涨价",
    "time": 1620987337,
    "image_links": [],
    "img_urls_original": [],
    "is_comment": false,
    "parent_pid": null,
    "floor": 814
  },
  {
    "pid": 139298901317,
    "tid": 7339397421,
    "user_name": "公孙闬",
    "user_id": 384316858,
    "text": "161.老婆坦言怀上我最好兄弟的孩子。我：双厨狂喜！",
    "time": 1620987342,
    "image_links": [],
    "img_urls_original": [],
    "is_comment": false,
    "parent_pid": null,
    "floor": 815
  },
  {
    "pid": 139298903016,
    "tid": 7339397421,
    "user_name": "公孙闬",
    "user_id": 384316858,
    "text": "160.女孩子晚上出门扔垃圾一定记得要带上垃圾",
    "time": 1620987349,
    "image_links": [],
    "img_urls_original": [],
    "is_comment": false,
    "parent_pid": null,
    "floor": 816
  },
  {
    "pid": 139299247707,
    "tid": 7339397421,
    "user_name": "鲤鱼zly",
    "user_id": 1208806729,
    "text": "gkd，母猪都没楼主能歇",
    "time": 1620988804,
    "image_links": [],
    "img_urls_original": [],
    "is_comment": false,
    "parent_pid": null,
    "floor": 817
  }
]