[
  {
    "pid": 147291629025,
    "tid": 7708339765,
    "user_name": "起飞5170",
    "user_id": 5574851511,
    "text": "3",
    "time": 1680696181,
    "image_links": [],
    "img_urls_original": [],
    "is_comment": false,
    "parent_pid": null,
    "floor": 2759
  },
  {
    "pid": 147294126552,
    "tid": 7708339765,
    "user_name": "",
    "user_id": 4091747390,
    "text": "第一次這個麼早😍😍😍我要給你裝上監視器、😚😚監視你的一舉一動😋😋😋我要給你裝上竊聽器，你的一言一行都是這麼的泌人心脾😍😍😍我要舔你家的浴缸🛁🛁🛁我要用你的牙刷😘😘😘你是我的🤑🤑🤑你不能和別人講話😭😭😭你只能屬於我🤤🤤🤤❤️❤️❤️❤️❤️💝💝💝",
    "time": 1680716015,
    "image_links": [],
    "img_urls_original": [],
    "is_comment": false,
    "parent_pid": null,
    "floor": 2761
  },
  {
    "pid": 147294324655,
    "tid": 7708339765,
    "user_name": "妥啦基",
    "user_id": 1337422201,
    "text": "3",
    "time": 1680718682,
    "image_links": [],
    "img_urls_original": [],
    "is_comment": false,
    "parent_pid": null,
    "floor": 2763
  },
  {
    "pid": 147295547893,
    "tid": 7708339765,
    "user_name": "贴吧江西醉帅",
    "user_id": 4943354858,
    "text": "3",
    "time": 1680740789,
    "image_links": [],
    "img_urls_original": [],
    "is_comment": false,
    "parent_pid": null,
    "floor": 2764
  },
  {
    "pid": 147295941512,
    "tid": 7708339765,
    "user_name": "爹就不打扰你了",
    "user_id": 1477797851,
    "text": "3",
    "time": 1680744241,
    "image_links": [],
    "img_urls_original": [],
    "is_comment": false,
    "parent_pid": null,
    "floor": 2766
  },
  {
    "pid": 147298969045,
    "tid": 7708339765,
    "user_name": "",
    "user_id": 4179261009,
    "text": "。。",
    "time": 1680767408,
    "image_links": [],
    "img_urls_original": [],
    "is_comment": false,
    "parent_pid": null,
    "floor": 2767
  },
  {
    "pid": 147299166856,
    "tid": 7708339765,
    "user_name": "",
    "user_id": 3567854178,
    "text": "3",
    "time": 1680768848,
    "image_links": [],
    "img_urls_original": [],
    "is_comment": false,
    "parent_pid": null,
    "floor": 2768
  },
  {
    "pid": 147299167379,
    "tid": 7708339765,
    "user_name": "",
    "user_id": 3567854178,
    "text": "3",
    "time": 1680768851,
    "image_links": [],
    "img_urls_original": [],
    "is_comment": false,
    "parent_pid": null,
    "floor": 2769
  },
  {
    "pid": 147299167835,
    "tid": 7708339765,
    "user_name": "",
    "user_id": 3567854178,
    "text": "3",
    "time": 1680768855,
    "image_links": [],
    "img_urls_original": [],
    "is_comment": false,
    "parent_pid": null,
    "floor": 2770
  },
  {
    "pid": 147299168292,
    "tid": 7708339765,
    "user_name": "",
    "user_id": 3567854178,
    "text": "3",
    "time": 1680768858,
    "image_links": [],
    "img_urls_original": [],
    "is_comment": false,
    "parent_pid": null,
    "floor": 2771
  },
  {
    "pid": 147299813090,
    "tid": 7708339765,
    "user_name": "讨厌喧嚣世界",
    "user_id": 5731490473,
    "text": "",
    "time": 1680773698,
    "image_links": [
      "images/楼层_2772_147299813090_图片1.jpg"
    ],
    "img_urls_original": [
      "http://tiebapic.baidu.com/forum/pic/item/af0fcbfc1e178a8205fb9b6ab303738dab77e8db.jpg?tbpicau=2026-03-19-05_d323685febb350358568b82114dd0927"
    ],
    "is_comment": false,
    "parent_pid": null,
    "floor": 2772
  },
  {
    "pid": 147301874252,
    "tid": 7708339765,
    "user_name": "空殇亦冷",
    "user_id": 4910626700,
    "text": "立刻出院！",
    "time": 1680789575,
    "image_links": [],
    "img_urls_original": [],
    "is_comment": false,
    "parent_pid": null,
    "floor": 2774
  },
  {
    "pid": 147302342457,
    "tid": 7708339765,
    "user_name": "",
    "user_id": 2020909973,
    "text": "",
    "time": 1680793189,
    "image_links": [
      "images/楼层_2776_147302342457_图片1.jpg"
    ],
    "img_urls_original": [
      "http://tiebapic.baidu.com/forum/pic/item/bdc672c6a7efce1bdeca2800ea51f3deb68f65c4.jpg?tbpicau=2026-03-19-05_9f6d9c7b15a6e133a174da5ce67e56d7"
    ],
    "is_comment": false,
    "parent_pid": null,
    "floor": 2776
  },
  {
    "pid": 147302607785,
    "tid": 7708339765,
    "user_name": "兴奋的大母猴丶",
    "user_id": 2040238487,
    "text": "333",
    "time": 1680795295,
    "image_links": [],
    "img_urls_original": [],
    "is_comment": false,
    "parent_pid": null,
    "floor": 2777
  },
  {
    "pid": 147302928379,
    "tid": 7708339765,
    "user_name": "sky丨发呆",
    "user_id": 1372752108,
    "text": "3",
    "time": 1680797848,
    "image_links": [],
    "img_urls_original": [],
    "is_comment": false,
    "parent_pid": null,
    "floor": 2778
  },
  {
    "pid": 147303155929,
    "tid": 7708339765,
    "user_name": "ntr张欣航",
    "user_id": 6094020314,
    "text": "3",
    "time": 1680799855,
    "image_links": [],
    "img_urls_original": [],
    "is_comment": false,
    "parent_pid": null,
    "floor": 2779
  },
  {
    "pid": 147305461571,
    "tid": 7708339765,
    "user_name": "夕hdjjs颜",
    "user_id": 4057176808,
    "text": "",
    "time": 1680831994,
    "image_links": [
      "images/楼层_2781_147305461571_图片1.jpg"
    ],
    "img_urls_original": [
      "http://tiebapic.baidu.com/forum/pic/item/d12a9645d688d43f7ca8fb38381ed21b0ff43ba4.jpg?tbpicau=2026-03-19-05_97079d2ffdcdf8a6ca7e5cde6c4ab69a"
    ],
    "is_comment": false,
    "parent_pid": null,
    "floor": 2781
  },
  {
    "pid": 147305506732,
    "tid": 7708339765,
    "user_name": "迷之彼女xx",
    "user_id": 1506282470,
    "text": "1",
    "time": 1680832348,
    "image_links": [],
    "img_urls_original": [],
    "is_comment": false,
    "parent_pid": null,
    "floor": 2782
  },
  {
    "pid": 147305535921,
    "tid": 7708339765,
    "user_name": "极拔狠鞑",
    "user_id": 2687716051,
    "text": "",
    "time": 1680832572,
    "image_links": [
      "images/楼层_2783_147305535921_图片1.jpg"
    ],
    "img_urls_original": [
      "http://tiebapic.baidu.com/forum/pic/item/e43e7b3e6709c93d19acdb3dda3df8dcd0005443.jpg?tbpicau=2026-03-19-05_6a05c0205b337848c95135057f9aada5"
    ],
    "is_comment": false,
    "parent_pid": null,
    "floor": 2783
  },
  {
    "pid": 147305765802,
    "tid": 7708339765,
    "user_name": "",
    "user_id": 5400612163,
    "text": "3",
    "time": 1680834289,
    "image_links": [],
    "img_urls_original": [],
    "is_comment": false,
    "parent_pid": null,
    "floor": 2784
  },
  {
    "pid": 147307604296,
    "tid": 7708339765,
    "user_name": "云深不见月A",
    "user_id": 4280573557,
    "text": "3",
    "time": 1680848284,
    "image_links": [],
    "img_urls_original": [],
    "is_comment": false,
    "parent_pid": null,
    "floor": 2787
  },
  {
    "pid": 147308891477,
    "tid": 7708339765,
    "user_name": "夏树抱抱",
    "user_id": 17596398034586,
    "text": "",
    "time": 1680857788,
    "image_links": [
      "images/楼层_2788_147308891477_图片1.jpg"
    ],
    "img_urls_original": [
      "http://tiebapic.baidu.com/forum/pic/item/19815adf8db1cb130cb6ecd99854564e90584bc2.jpg?tbpicau=2026-03-19-05_b22a6a17af28ef76af93109629a44cd3"
    ],
    "is_comment": false,
    "parent_pid": null,
    "floor": 2788
  }
]