[
  {
    "pid": 151429632105,
    "tid": 9354404050,
    "user_name": "公孙闬",
    "user_id": 384316858,
    "text": "195.“我让你把碳酸钠和盐酸拿来，怎么就拿来一瓶生理盐水？”“我道上混的。”\n评分：3.65",
    "time": 1735026180,
    "image_links": [],
    "img_urls_original": [],
    "is_comment": false,
    "parent_pid": null,
    "floor": 283
  },
  {
    "pid": 151429632847,
    "tid": 9354404050,
    "user_name": "公孙闬",
    "user_id": 384316858,
    "text": "194.王警官为了给伤者省钱，把凶手打伤后让他们拼救护车去医院。\n评分：3.65",
    "time": 1735026190,
    "image_links": [],
    "img_urls_original": [],
    "is_comment": false,
    "parent_pid": null,
    "floor": 284
  },
  {
    "pid": 151429633473,
    "tid": 9354404050,
    "user_name": "公孙闬",
    "user_id": 384316858,
    "text": "193.老王表演的绝技在千人剧场震惊四座，但是剩下的996人觉得还行。\n评分：3.65",
    "time": 1735026199,
    "image_links": [],
    "img_urls_original": [],
    "is_comment": false,
    "parent_pid": null,
    "floor": 285
  },
  {
    "pid": 151429634181,
    "tid": 9354404050,
    "user_name": "公孙闬",
    "user_id": 384316858,
    "text": "192.在家被老婆孩子欺压不敢吭声来公司拿领导出气\n评分：3.65",
    "time": 1735026208,
    "image_links": [],
    "img_urls_original": [],
    "is_comment": false,
    "parent_pid": null,
    "floor": 286
  },
  {
    "pid": 151429634801,
    "tid": 9354404050,
    "user_name": "公孙闬",
    "user_id": 384316858,
    "text": "191.积德行善的反义词是柯南行凶。\n评分：3.65",
    "time": 1735026217,
    "image_links": [],
    "img_urls_original": [],
    "is_comment": false,
    "parent_pid": null,
    "floor": 287
  },
  {
    "pid": 151429636088,
    "tid": 9354404050,
    "user_name": "公孙闬",
    "user_id": 384316858,
    "text": "190*.决赛地点在浙大教学楼主楼姜萍却来到了教学楼六楼\n评分：3.65",
    "time": 1735026235,
    "image_links": [],
    "img_urls_original": [],
    "is_comment": false,
    "parent_pid": null,
    "floor": 288
  },
  {
    "pid": 151429639959,
    "tid": 9354404050,
    "user_name": "公孙闬",
    "user_id": 384316858,
    "text": "189.清明祭祖，祖宗说外卖放门口\n评分：3.65",
    "time": 1735026289,
    "image_links": [],
    "img_urls_original": [],
    "is_comment": false,
    "parent_pid": null,
    "floor": 289
  },
  {
    "pid": 151429641686,
    "tid": 9354404050,
    "user_name": "公孙闬",
    "user_id": 384316858,
    "text": "188.这个世界出bug了，葬礼直播右上角却写着live。\n评分：3.65",
    "time": 1735026315,
    "image_links": [],
    "img_urls_original": [],
    "is_comment": false,
    "parent_pid": null,
    "floor": 290
  },
  {
    "pid": 151429642341,
    "tid": 9354404050,
    "user_name": "公孙闬",
    "user_id": 384316858,
    "text": "187.被骂老不死的王老汉一怒之下出示了自己的死亡证。\n评分：3.65",
    "time": 1735026324,
    "image_links": [],
    "img_urls_original": [],
    "is_comment": false,
    "parent_pid": null,
    "floor": 291
  },
  {
    "pid": 151429644698,
    "tid": 9354404050,
    "user_name": "公孙闬",
    "user_id": 384316858,
    "text": "186.车祸现场幸运小伙忘开体积碰撞逃过一劫\n评分：3.65",
    "time": 1735026357,
    "image_links": [],
    "img_urls_original": [],
    "is_comment": false,
    "parent_pid": null,
    "floor": 292
  },
  {
    "pid": 151429663104,
    "tid": 9354404050,
    "user_name": "公孙闬",
    "user_id": 384316858,
    "text": "185.ATM机防呆设计必须证明黎曼猜想才能转账\n评分：3.66",
    "time": 1735026615,
    "image_links": [],
    "img_urls_original": [],
    "is_comment": false,
    "parent_pid": null,
    "floor": 293
  },
  {
    "pid": 151429663836,
    "tid": 9354404050,
    "user_name": "公孙闬",
    "user_id": 384316858,
    "text": "184.磁悬浮列车扮鬼吓唬绿皮火车现已被有关部门全面禁止\n评分：3.66",
    "time": 1735026626,
    "image_links": [],
    "img_urls_original": [],
    "is_comment": false,
    "parent_pid": null,
    "floor": 294
  },
  {
    "pid": 151429664401,
    "tid": 9354404050,
    "user_name": "公孙闬",
    "user_id": 384316858,
    "text": "183.被核弹轰炸没弹出安全气囊向车厂索赔无果\n评分：3.66",
    "time": 1735026634,
    "image_links": [],
    "img_urls_original": [],
    "is_comment": false,
    "parent_pid": null,
    "floor": 295
  },
  {
    "pid": 151429665134,
    "tid": 9354404050,
    "user_name": "公孙闬",
    "user_id": 384316858,
    "text": "182.多功能婴儿床煎炒两用\n评分：3.66",
    "time": 1735026644,
    "image_links": [],
    "img_urls_original": [],
    "is_comment": false,
    "parent_pid": null,
    "floor": 296
  },
  {
    "pid": 151429665820,
    "tid": 9354404050,
    "user_name": "公孙闬",
    "user_id": 384316858,
    "text": "181.甜甜圈是去中心化的面包。\n评分：3.66",
    "time": 1735026653,
    "image_links": [],
    "img_urls_original": [],
    "is_comment": false,
    "parent_pid": null,
    "floor": 297
  },
  {
    "pid": 151429666552,
    "tid": 9354404050,
    "user_name": "公孙闬",
    "user_id": 384316858,
    "text": "180.冷知识:人的屁股上有一个孔，是为了防止食人族小孩误食。\n评分：3.66",
    "time": 1735026663,
    "image_links": [],
    "img_urls_original": [],
    "is_comment": false,
    "parent_pid": null,
    "floor": 298
  },
  {
    "pid": 151429667217,
    "tid": 9354404050,
    "user_name": "公孙闬",
    "user_id": 384316858,
    "text": "179.唐僧师徒不小心把取得的经文弄丢在通天河，徒弟们只好劝他:“老大，西游again!”\n评分：3.67",
    "time": 1735026672,
    "image_links": [],
    "img_urls_original": [],
    "is_comment": false,
    "parent_pid": null,
    "floor": 299
  },
  {
    "pid": 151429667860,
    "tid": 9354404050,
    "user_name": "公孙闬",
    "user_id": 384316858,
    "text": "178.电瓶车的花语是什么\n评分：3.67",
    "time": 1735026681,
    "image_links": [],
    "img_urls_original": [],
    "is_comment": false,
    "parent_pid": null,
    "floor": 300
  },
  {
    "pid": 151429668530,
    "tid": 9354404050,
    "user_name": "公孙闬",
    "user_id": 384316858,
    "text": "177.既然台上一分钟，台下十年功，那为什么不直接在台上练功?\n评分：3.67",
    "time": 1735026690,
    "image_links": [],
    "img_urls_original": [],
    "is_comment": false,
    "parent_pid": null,
    "floor": 301
  },
  {
    "pid": 151429669189,
    "tid": 9354404050,
    "user_name": "公孙闬",
    "user_id": 384316858,
    "text": "176.开会的时候只有18g水要分给6.02x10^23个领导该怎么分?\n评分：3.67",
    "time": 1735026699,
    "image_links": [],
    "img_urls_original": [],
    "is_comment": false,
    "parent_pid": null,
    "floor": 302
  },
  {
    "pid": 151429718882,
    "tid": 9354404050,
    "user_name": "知道哥是谁吗",
    "user_id": 222524787,
    "text": "求更",
    "time": 1735027361,
    "image_links": [],
    "img_urls_original": [],
    "is_comment": false,
    "parent_pid": null,
    "floor": 308
  },
  {
    "pid": 151429724946,
    "tid": 9354404050,
    "user_name": "最后的黄昏l",
    "user_id": 2872101515,
    "text": "快更",
    "time": 1735027441,
    "image_links": [],
    "img_urls_original": [],
    "is_comment": false,
    "parent_pid": null,
    "floor": 309
  },
  {
    "pid": 151429793141,
    "tid": 9354404050,
    "user_name": "广告iiiii",
    "user_id": 3254632174,
    "text": "赶紧把前几名发出来",
    "time": 1735028362,
    "image_links": [],
    "img_urls_original": [],
    "is_comment": false,
    "parent_pid": null,
    "floor": 310
  },
  {
    "pid": 151429801065,
    "tid": 9354404050,
    "user_name": "goat110",
    "user_id": 32390404,
    "text": "那么这个年历在哪里可以买得到呢",
    "time": 1735028469,
    "image_links": [],
    "img_urls_original": [],
    "is_comment": false,
    "parent_pid": null,
    "floor": 311
  },
  {
    "pid": 151429814670,
    "tid": 9354404050,
    "user_name": "令君与魏王",
    "user_id": 4500289691,
    "text": "速速速速",
    "time": 1735028658,
    "image_links": [],
    "img_urls_original": [],
    "is_comment": false,
    "parent_pid": null,
    "floor": 312
  },
  {
    "pid": 151429835568,
    "tid": 9354404050,
    "user_name": "汪汪汪汪汪汪26",
    "user_id": 2321188985,
    "text": "快快更新",
    "time": 1735028946,
    "image_links": [],
    "img_urls_original": [],
    "is_comment": false,
    "parent_pid": null,
    "floor": 313
  },
  {
    "pid": 151429847673,
    "tid": 9354404050,
    "user_name": "锕镧X",
    "user_id": 4119132568,
    "text": "好好好",
    "time": 1735029119,
    "image_links": [],
    "img_urls_original": [],
    "is_comment": false,
    "parent_pid": null,
    "floor": 314
  },
  {
    "pid": 151429922214,
    "tid": 9354404050,
    "user_name": "雨寒430",
    "user_id": 6383763284,
    "text": "快更",
    "time": 1735030151,
    "image_links": [],
    "img_urls_original": [],
    "is_comment": false,
    "parent_pid": null,
    "floor": 315
  },
  {
    "pid": 151429968910,
    "tid": 9354404050,
    "user_name": "匿名户不存在",
    "user_id": 1078936673,
    "text": "烂完了",
    "time": 1735030773,
    "image_links": [],
    "img_urls_original": [],
    "is_comment": false,
    "parent_pid": null,
    "floor": 316
  }
]