[
  {
    "pid": 152744082258,
    "tid": 10130417881,
    "user_name": "公孙闬",
    "user_id": 384316858,
    "text": "",
    "time": 1760586264,
    "image_links": [
      "images/楼层_1_152744082258_图片1.jpg",
      "images/楼层_1_152744082258_图片2.jpg"
    ],
    "img_urls_original": [
      "http://tiebapic.baidu.com/forum/pic/item/e41474cf3bc79f3d3473ae27fca1cd11738b29c4.jpg?tbpicau=2026-03-19-05_4a666eeeb22a78a191801850ca7c04d3",
      "http://tiebapic.baidu.com/forum/pic/item/73f689b1cb134954a28ca273104e9258d0094ac4.jpg?tbpicau=2026-03-19-05_d9910675874f9efd830b0d4d5d34b45e"
    ],
    "is_comment": false,
    "parent_pid": null,
    "floor": 1
  },
  {
    "pid": 152744084054,
    "tid": 10130417881,
    "user_name": "公孙闬",
    "user_id": 384316858,
    "text": "",
    "time": 1760586296,
    "image_links": [
      "images/楼层_2_152744084054_图片1.jpg"
    ],
    "img_urls_original": [
      "http://tiebapic.baidu.com/forum/pic/item/8631932bd40735fa0b7d04aed8510fb30e2408c5.jpg?tbpicau=2026-03-19-05_7bc37e6e0eaaf1f6b581950bbb46b21e"
    ],
    "is_comment": false,
    "parent_pid": null,
    "floor": 2
  },
  {
    "pid": 152744085311,
    "tid": 10130417881,
    "user_name": "公孙闬",
    "user_id": 384316858,
    "text": "",
    "time": 1760586318,
    "image_links": [
      "images/楼层_3_152744085311_图片1.jpg"
    ],
    "img_urls_original": [
      "http://tiebapic.baidu.com/forum/pic/item/5de63fc79f3df8dc1cb1c5868b11728b461028c6.jpg?tbpicau=2026-03-19-05_4721fcae7a51025da7da15b26f341038"
    ],
    "is_comment": false,
    "parent_pid": null,
    "floor": 3
  },
  {
    "pid": 152744086550,
    "tid": 10130417881,
    "user_name": "公孙闬",
    "user_id": 384316858,
    "text": "",
    "time": 1760586340,
    "image_links": [
      "images/楼层_4_152744086550_图片1.jpg"
    ],
    "img_urls_original": [
      "http://tiebapic.baidu.com/forum/pic/item/9788c911728b47106ba0b7db85cec3fdfd0323c7.jpg?tbpicau=2026-03-19-05_5a50d0cf7ce888eb5afdd7ba4c370697"
    ],
    "is_comment": false,
    "parent_pid": null,
    "floor": 4
  },
  {
    "pid": 152744087579,
    "tid": 10130417881,
    "user_name": "公孙闬",
    "user_id": 384316858,
    "text": "",
    "time": 1760586357,
    "image_links": [
      "images/楼层_5_152744087579_图片1.jpg"
    ],
    "img_urls_original": [
      "http://tiebapic.baidu.com/forum/pic/item/8ac6ca1b9d16fdfa35e28cf9f28f8c5495ee7bc0.jpg?tbpicau=2026-03-19-05_216004b04d913600f58d49c2b80d19c5"
    ],
    "is_comment": false,
    "parent_pid": null,
    "floor": 5
  },
  {
    "pid": 152744088473,
    "tid": 10130417881,
    "user_name": "公孙闬",
    "user_id": 384316858,
    "text": "",
    "time": 1760586372,
    "image_links": [
      "images/楼层_6_152744088473_图片1.jpg"
    ],
    "img_urls_original": [
      "http://tiebapic.baidu.com/forum/pic/item/27f866d9f2d3572c236bd6cbcc13632763d0c3c1.jpg?tbpicau=2026-03-19-05_afe9bc392e12fb699903949d5c2656cb"
    ],
    "is_comment": false,
    "parent_pid": null,
    "floor": 6
  },
  {
    "pid": 152744089194,
    "tid": 10130417881,
    "user_name": "公孙闬",
    "user_id": 384316858,
    "text": "",
    "time": 1760586385,
    "image_links": [
      "images/楼层_7_152744089194_图片1.jpg"
    ],
    "img_urls_original": [
      "http://tiebapic.baidu.com/forum/pic/item/8b37acd3fd1f413428be4f69631f95cad0c85ec1.jpg?tbpicau=2026-03-19-05_56317ab265154bfca625aa6ac1e4ece6"
    ],
    "is_comment": false,
    "parent_pid": null,
    "floor": 7
  },
  {
    "pid": 152744089980,
    "tid": 10130417881,
    "user_name": "公孙闬",
    "user_id": 384316858,
    "text": "",
    "time": 1760586399,
    "image_links": [
      "images/楼层_8_152744089980_图片1.jpg"
    ],
    "img_urls_original": [
      "http://tiebapic.baidu.com/forum/pic/item/baf4a544ad345982cb02af854af431adcaef84c2.jpg?tbpicau=2026-03-19-05_d79708663936a7637bbd86426d9a163c"
    ],
    "is_comment": false,
    "parent_pid": null,
    "floor": 8
  },
  {
    "pid": 152744091126,
    "tid": 10130417881,
    "user_name": "公孙闬",
    "user_id": 384316858,
    "text": "",
    "time": 1760586419,
    "image_links": [
      "images/楼层_9_152744091126_图片1.jpg"
    ],
    "img_urls_original": [
      "http://tiebapic.baidu.com/forum/pic/item/c479312ac65c10383ff584d5f4119313b17e89c3.jpg?tbpicau=2026-03-19-05_d6e684e524c3d57a0fbad3185972d234"
    ],
    "is_comment": false,
    "parent_pid": null,
    "floor": 9
  },
  {
    "pid": 152744092382,
    "tid": 10130417881,
    "user_name": "公孙闬",
    "user_id": 384316858,
    "text": "",
    "time": 1760586441,
    "image_links": [
      "images/楼层_10_152744092382_图片1.jpg"
    ],
    "img_urls_original": [
      "http://tiebapic.baidu.com/forum/pic/item/17aeed50352ac65c7b8f2c64bdf2b21192138acc.jpg?tbpicau=2026-03-19-05_3b87b96de33bbd5c55e9950db7758467"
    ],
    "is_comment": false,
    "parent_pid": null,
    "floor": 10
  },
  {
    "pid": 152744096974,
    "tid": 10130417881,
    "user_name": "老蔡思慕",
    "user_id": 5469031497,
    "text": "笑死了",
    "time": 1760586522,
    "image_links": [],
    "img_urls_original": [],
    "is_comment": false,
    "parent_pid": null,
    "floor": 11
  },
  {
    "pid": 152744521467,
    "tid": 10130417881,
    "user_name": "活着_直到死去",
    "user_id": 6721642381,
    "text": "我喜欢你",
    "time": 1760594373,
    "image_links": [],
    "img_urls_original": [],
    "is_comment": false,
    "parent_pid": null,
    "floor": 12
  },
  {
    "pid": 152744575074,
    "tid": 10130417881,
    "user_name": "小叶榕Ya",
    "user_id": 4339803223,
    "text": "你是",
    "time": 1760595326,
    "image_links": [],
    "img_urls_original": [],
    "is_comment": false,
    "parent_pid": null,
    "floor": 13
  },
  {
    "pid": 152744603496,
    "tid": 10130417881,
    "user_name": "儒雅的mirago",
    "user_id": 5550080627,
    "text": "最出圈的段子却不能出院，说明圈外是个更大的病院",
    "time": 1760595819,
    "image_links": [],
    "img_urls_original": [],
    "is_comment": false,
    "parent_pid": null,
    "floor": 14
  },
  {
    "pid": 152744628103,
    "tid": 10130417881,
    "user_name": "quballr",
    "user_id": 341595860,
    "text": "这些段子小时候抱过我",
    "time": 1760596253,
    "image_links": [],
    "img_urls_original": [],
    "is_comment": false,
    "parent_pid": null,
    "floor": 15
  },
  {
    "pid": 152744771213,
    "tid": 10130417881,
    "user_name": "",
    "user_id": 5848280516,
    "text": "鱼被凌迟叫鱼生那个我印象很深",
    "time": 1760598737,
    "image_links": [],
    "img_urls_original": [],
    "is_comment": false,
    "parent_pid": null,
    "floor": 16
  },
  {
    "pid": 152744838170,
    "tid": 10130417881,
    "user_name": "邪眸浅笑",
    "user_id": 1947186795,
    "text": "查个眼",
    "time": 1760599926,
    "image_links": [],
    "img_urls_original": [],
    "is_comment": false,
    "parent_pid": null,
    "floor": 19
  },
  {
    "pid": 152744882158,
    "tid": 10130417881,
    "user_name": "Teamby_",
    "user_id": 6593435110,
    "text": "好",
    "time": 1760600704,
    "image_links": [],
    "img_urls_original": [],
    "is_comment": false,
    "parent_pid": null,
    "floor": 20
  },
  {
    "pid": 152744918833,
    "tid": 10130417881,
    "user_name": "神净讨魔先生",
    "user_id": 4532580642,
    "text": "真的好快，都21年了",
    "time": 1760601354,
    "image_links": [],
    "img_urls_original": [],
    "is_comment": false,
    "parent_pid": null,
    "floor": 21
  },
  {
    "pid": 152744964010,
    "tid": 10130417881,
    "user_name": "帝宝的训练员",
    "user_id": 6394272977,
    "text": "我才22岁\n难忘同草重家秀、游王子亚情、朱颜浴琴、从一玉华、共由雨玲、周防宇婷、弓野虽萱、走之义QQ度过的那些年",
    "time": 1760602129,
    "image_links": [],
    "img_urls_original": [],
    "is_comment": false,
    "parent_pid": null,
    "floor": 22
  },
  {
    "pid": 152745027775,
    "tid": 10130417881,
    "user_name": "NecDazf",
    "user_id": 6500133603,
    "text": "弱智吧，生日快乐！",
    "time": 1760603224,
    "image_links": [],
    "img_urls_original": [],
    "is_comment": false,
    "parent_pid": null,
    "floor": 23
  },
  {
    "pid": 152745073902,
    "tid": 10130417881,
    "user_name": "小萌之歌",
    "user_id": 699562820,
    "text": "明明我才24岁，我的人生没等发挥就要挥发。",
    "time": 1760603971,
    "image_links": [],
    "img_urls_original": [],
    "is_comment": false,
    "parent_pid": null,
    "floor": 24
  },
  {
    "pid": 152745218093,
    "tid": 10130417881,
    "user_name": "氯化聚氯乙烯",
    "user_id": 3559172978,
    "text": "孤的败看一次笑一次",
    "time": 1760606523,
    "image_links": [],
    "img_urls_original": [],
    "is_comment": false,
    "parent_pid": null,
    "floor": 26
  },
  {
    "pid": 152745228973,
    "tid": 10130417881,
    "user_name": "天空鸟的梦回",
    "user_id": 6826648858,
    "text": "我们都是弱智儿童捏～",
    "time": 1760606681,
    "image_links": [],
    "img_urls_original": [],
    "is_comment": false,
    "parent_pid": null,
    "floor": 27
  },
  {
    "pid": 152745406091,
    "tid": 10130417881,
    "user_name": "____Gold____",
    "user_id": 2594905675,
    "text": "弱智吧好！",
    "time": 1760609756,
    "image_links": [],
    "img_urls_original": [],
    "is_comment": false,
    "parent_pid": null,
    "floor": 28
  },
  {
    "pid": 152745711452,
    "tid": 10130417881,
    "user_name": "东平郡王李延庆",
    "user_id": 6532898764,
    "text": "生日是什么体位？快乐又是谁？还有，羡慕弱智吧",
    "time": 1760615249,
    "image_links": [],
    "img_urls_original": [],
    "is_comment": false,
    "parent_pid": null,
    "floor": 33
  },
  {
    "pid": 152745848000,
    "tid": 10130417881,
    "user_name": "神秘花园药剂师",
    "user_id": 5735684840,
    "text": "贺",
    "time": 1760617826,
    "image_links": [],
    "img_urls_original": [],
    "is_comment": false,
    "parent_pid": null,
    "floor": 35
  },
  {
    "pid": 152745855403,
    "tid": 10130417881,
    "user_name": "赞美金色大只佬",
    "user_id": 6684329409,
    "text": "生日快乐喵",
    "time": 1760617969,
    "image_links": [],
    "img_urls_original": [],
    "is_comment": false,
    "parent_pid": null,
    "floor": 36
  },
  {
    "pid": 152745865898,
    "tid": 10130417881,
    "user_name": "NDKXHD",
    "user_id": 5987746892,
    "text": "太阳那么大，生出来会很辛苦吧，真的会快乐吗？",
    "time": 1760618166,
    "image_links": [],
    "img_urls_original": [],
    "is_comment": false,
    "parent_pid": null,
    "floor": 37
  },
  {
    "pid": 152745877032,
    "tid": 10130417881,
    "user_name": "黑色柠檬awa",
    "user_id": 6716285557,
    "text": "生日快乐",
    "time": 1760618373,
    "image_links": [],
    "img_urls_original": [],
    "is_comment": false,
    "parent_pid": null,
    "floor": 38
  }
]